anyblob/__init__.py
anyblob/_blob.py
anyblob-1.0.1.dist-info/LICENSE
anyblob-1.0.1.dist-info/WHEEL
anyblob-1.0.1.dist-info/METADATA
anyblob-1.0.1.dist-info/RECORD
