Metadata-Version: 2.1
Name: anyblob
Version: 1.0.1
Summary: 
License: MIT
Author: Danilo Horta
Author-email: danilo.horta@pm.me
Requires-Python: >=3.10,<4.0
Classifier: License :: OSI Approved :: MIT License
Classifier: Programming Language :: Python :: 3
Classifier: Programming Language :: Python :: 3.10
Classifier: Programming Language :: Python :: 3.11
Requires-Dist: pooch (>=1.6.0,<2.0.0)
